rsLogger/__init__.py
rsLogger/logger.py
rsLogger-1.1.0.dist-info/LICENSE
rsLogger-1.1.0.dist-info/METADATA
rsLogger-1.1.0.dist-info/WHEEL
rsLogger-1.1.0.dist-info/entry_points.txt
rsLogger-1.1.0.dist-info/top_level.txt
rsLogger-1.1.0.dist-info/RECORD
