Metadata-Version: 2.1
Name: rsLogger
Version: 1.1.0
Summary: A simple logger for python projects
Author-email: Adrian Causby <frankie@ramseysystems.co.uk>
License: MIT License
Project-URL: Homepage, https://github.com/RamseySystems/rsLogger.git
Keywords: logging,logger,python
Classifier: License :: OSI Approved :: MIT License
Classifier: Programming Language :: Python :: 3
Classifier: Programming Language :: Python :: 3.6
Requires-Python: >=3.6
License-File: LICENSE
Provides-Extra: dev
Requires-Dist: pytest; extra == "dev"
Requires-Dist: pytest-cov; extra == "dev"
Requires-Dist: flake8; extra == "dev"
Requires-Dist: black; extra == "dev"
Requires-Dist: isort; extra == "dev"
